text_class_retail/__init__.py
text_class_retail/ds_tree.joblib
text_class_retail/logreg.joblib
text_class_retail/predictor.py
text_class_retail/rd_forest.joblib
text_class_retail-0.1.dist-info/LICENSE.txt
text_class_retail-0.1.dist-info/METADATA
text_class_retail-0.1.dist-info/WHEEL
text_class_retail-0.1.dist-info/top_level.txt
text_class_retail-0.1.dist-info/RECORD
