Metadata-Version: 2.1
Name: text-class-retail
Version: 0.1
License-File: LICENSE.txt
Requires-Dist: scikit-learn
Requires-Dist: joblib
Requires-Dist: os
